py_solidity_vuln_db/__init__.py
py_solidity_vuln_db/downloader.py
solidity_vulnerabilities_db2-2.0.0.dist-info/METADATA
solidity_vulnerabilities_db2-2.0.0.dist-info/WHEEL
solidity_vulnerabilities_db2-2.0.0.dist-info/top_level.txt
solidity_vulnerabilities_db2-2.0.0.dist-info/RECORD
