Metadata-Version: 2.4
Name: solidity-vulnerabilities-db2
Version: 2.0.0
Summary: Smart contract vulnerability templates for ReinforcedAI
Author: ReinforcedAI
Requires-Python: >=3.11
Dynamic: author
Dynamic: description
Dynamic: description-content-type
Dynamic: requires-python
Dynamic: summary
